changewords
