Metadata-Version: 1.1
Name: changewords
Version: 1.0.1
Summary: Python tool to change or replace the strings in files.
Home-page: https://github.com/agusmakmun/changewords/
Author: Agus Makmun (Summon Agus)
Author-email: summon.agus@gmail.com
License: MIT
Download-URL: https://github.com/agusmakmun/changewords/tarball/v1.0.0
Keywords: change words,word replacer,python tool
Platform: Linux
Classifier: Development Status :: 5 - Production/Stable
Classifier: License :: OSI Approved :: MIT License
Classifier: Operating System :: POSIX :: Linux
Classifier: Intended Audience :: Developers
Classifier: Programming Language :: Python :: 2
Classifier: Programming Language :: Python :: 2.6
Classifier: Programming Language :: Python :: 2.7
Classifier: Programming Language :: Python :: 3.0
Classifier: Programming Language :: Python :: 3.5
Classifier: Programming Language :: Python :: 3.6
Classifier: Topic :: Text Processing
Classifier: Topic :: Text Processing :: Filters
Classifier: Topic :: Text Processing :: Indexing
Classifier: Topic :: Software Development
